nomad_gui/__init__.py
nomad_gui/apis/__init__.py
nomad_gui/apis/static/.empty
nomad_gui/apis/static/config.js
nomad_gui/apis/static/favicon.ico
nomad_gui/apis/static/index.html
nomad_gui/apis/static/manifest.json
nomad_gui/apis/static/metainfo.js
nomad_gui/apis/static/mockServiceWorker.js
nomad_gui/apis/static/robots.txt
nomad_gui/apis/static/sample.bmp
nomad_gui/apis/static/sample.gif
nomad_gui/apis/static/sample.jpg
nomad_gui/apis/static/sample.json
nomad_gui/apis/static/sample.md
nomad_gui/apis/static/sample.pdf
nomad_gui/apis/static/sample.png
nomad_gui/apis/static/sample.svg
nomad_gui/apis/static/sample.tif
nomad_gui/apis/static/sample.txt
nomad_gui/apis/static/sample.webp
nomad_gui/apis/static/assets/AppearanceSubpage-BXYtCNYQ.js
nomad_gui/apis/static/assets/Boolean-Di5N5gPt.js
nomad_gui/apis/static/assets/ControlledDataTable-DvZXjuQB.js
nomad_gui/apis/static/assets/CopyToClipboard-pq4dp3BD.js
nomad_gui/apis/static/assets/Datetime-C5IF8FhX.js
nomad_gui/apis/static/assets/Download-BLwTLAkE.js
nomad_gui/apis/static/assets/Entries-Cb-7cqoF.js
nomad_gui/apis/static/assets/EntryContext-Jf9Y8HEC.js
nomad_gui/apis/static/assets/EntryDataEditor-BUx_eUm7.js
nomad_gui/apis/static/assets/EntryLogs-DBS9DzjI.js
nomad_gui/apis/static/assets/EntryOverview-0Zqi8b_z.js
nomad_gui/apis/static/assets/EntryOverview-B6EuTwBB.js
nomad_gui/apis/static/assets/EntryPage-BP2UJOfe.js
nomad_gui/apis/static/assets/EntryPage-DWCFmkko.js
nomad_gui/apis/static/assets/EntrySection-BoXFS5Wd.js
nomad_gui/apis/static/assets/EntrySection-CKWYx10N.js
nomad_gui/apis/static/assets/EntrySection-CUWxjQ7J.css
nomad_gui/apis/static/assets/EntrySubSectionTable-Darh7_Dh.js
nomad_gui/apis/static/assets/ErrorBoundary-Br5Se2a5.js
nomad_gui/apis/static/assets/GroupPage-B26jBIWz.js
nomad_gui/apis/static/assets/GroupPage-Br56rb_-.js
nomad_gui/apis/static/assets/GroupsPage-B2v3oQTZ.js
nomad_gui/apis/static/assets/GroupsPage-Bs7WLYiu.js
nomad_gui/apis/static/assets/HDF5FileViewer-BFuoaTl_.css
nomad_gui-2.0.0a1.dist-info/METADATA
nomad_gui-2.0.0a1.dist-info/WHEEL
nomad_gui-2.0.0a1.dist-info/entry_points.txt
nomad_gui-2.0.0a1.dist-info/top_level.txt
nomad_gui-2.0.0a1.dist-info/RECORD
