Metadata-Version: 2.4
Name: nomad-gui
Version: 2.0.0a1
Summary: NOMAD plugin containing the default graphical user interface.
Author-email: NOMAD Laboratory <markus.scheidgen@physik.hu-berlin.de>
Project-URL: Homepage, https://gitlab.mpcdf.mpg.de/nomad-lab/nomad-gui
Requires-Python: >=3.9
Requires-Dist: nomad-lab[infrastructure,parsing]>=1.3.17.dev161
Requires-Dist: pydantic
Provides-Extra: dev
Requires-Dist: ruff; extra == "dev"
Requires-Dist: pytest; extra == "dev"
Requires-Dist: nomad-schema-plugin-run>=1.0.1; extra == "dev"
Requires-Dist: mdanalysis<3.0.0,>=2.8.0; python_full_version >= "3.10" and extra == "dev"
Requires-Dist: mdanalysis<2.8; python_full_version < "3.10" and extra == "dev"
Requires-Dist: scipy>=1.7.1; extra == "dev"
Requires-Dist: networkx>=2.6.3; extra == "dev"
